{
  "entries": {
    "6681152659205225093" : {
      "status": "REVOKED",
      "reason": "KEY_COMPROMISE"
    },
    "8350192447815228107" : {
      "status": "REVOKED",
      "reason": "KEY_COMPROMISE"
    },
    "9408173275444922801" : {
      "status": "REVOKED",
      "reason": "KEY_COMPROMISE"
    },
    "11244410301401252959" : {
      "status": "REVOKED",
      "reason": "KEY_COMPROMISE"
    },
    "15346629759498347257" : {
      "status": "REVOKED",
      "reason": "KEY_COMPROMISE"
    },
    "1228286566665971148" : {
      "status": "REVOKED",
      "reason": "KEY_COMPROMISE"
    },
    "17471682139930361099" : {
      "status": "REVOKED",
      "reason": "SOFTWARE_FLAW"
    },
    "1545991490585406285": {
      "status": "REVOKED",
      "reason": "KEY_COMPROMISE"
    },
    "16799496319142405818": {
      "status": "REVOKED",
      "reason": "KEY_COMPROMISE"
    },
    "2621004353020741590": {
      "status": "REVOKED",
      "reason": "KEY_COMPROMISE"
    },
    "1051246719628187981": {
      "status": "REVOKED",
      "reason": "KEY_COMPROMISE"
    },
    "c35747a084470c3135aeefe2b8d40cd6": {
      "status": "REVOKED",
      "reason": "KEY_COMPROMISE"
    },
    "ee3ac673107ddf0831027a84c532bee4": {
      "status": "REVOKED",
      "reason": "KEY_COMPROMISE"
    },
    "1f4363f4acefdf83ae59202b934cead9": {
      "status": "REVOKED",
      "reason": "KEY_COMPROMISE"
    },
    "633d72164968d2b7ec1a927a14c8efbe": {
      "status": "REVOKED",
      "reason": "KEY_COMPROMISE"
    }
  }
}
